{
  "rows": [
    {
      "method": "ditto_concat_personal",
      "scenario": "FR_S0_congruent_iid",
      "seed": 11,
      "round": 1,
      "loss": 0.5748108169641338,
      "auroc": 0.7801825476429288,
      "auprc": 0.47151465999823083,
      "acc": 0.785084202085004,
      "f1": 0.5197132616487455,
      "threshold": 0.3999999999999999,
      "num_selected_clients": 10,
      "selected_clients": "0,1,2,3,4,5,6,7,8,9",
      "val_loss": 0.574094426813034,
      "val_auroc": 0.7856374999999999,
      "val_auprc": 0.5179359194685568,
      "val_acc": 0.78,
      "val_f1": 0.5089285714285714,
      "train_loss": 12.071403681952942,
      "train_auroc": 0.5999638008744576,
      "train_auprc": 0.2609216891401752,
      "train_acc": 0.7996434143080009,
      "train_f1": 0.0,
      "is_personalized": true,
      "variant": "personal"
    },
    {
      "method": "ditto_concat_personal",
      "scenario": "FR_S0_congruent_iid",
      "seed": 11,
      "round": 2,
      "loss": 0.5213211024460501,
      "auroc": 0.8384974924774323,
      "auprc": 0.589129664576608,
      "acc": 0.8251804330392943,
      "f1": 0.5439330543933054,
      "threshold": 0.3449999999999999,
      "num_selected_clients": 10,
      "selected_clients": "0,1,2,3,4,5,6,7,8,9",
      "val_loss": 0.518753821664112,
      "val_auroc": 0.8628250000000001,
      "val_auprc": 0.6352794784229421,
      "val_acc": 0.856,
      "val_f1": 0.6170212765957447,
      "train_loss": 13.423687480674014,
      "train_auroc": 0.678336779111512,
      "train_auprc": 0.35040327238918584,
      "train_acc": 0.7996434143080009,
      "train_f1": 0.0,
      "is_personalized": true,
      "variant": "personal"
    },
    {
      "method": "ditto_concat_personal",
      "scenario": "FR_S0_congruent_iid",
      "seed": 11,
      "round": 3,
      "loss": 0.4810104198185846,
      "auroc": 0.8614242728184553,
      "auprc": 0.6304782999485514,
      "acc": 0.830793905372895,
      "f1": 0.5902912621359223,
      "threshold": 0.285,
      "num_selected_clients": 10,
      "selected_clients": "0,1,2,3,4,5,6,7,8,9",
      "val_loss": 0.4763319018778551,
      "val_auroc": 0.8922375,
      "val_auprc": 0.6858450739940966,
      "val_acc": 0.858,
      "val_f1": 0.6432160804020101,
      "train_loss": 15.602319544398336,
      "train_auroc": 0.7717651381955922,
      "train_auprc": 0.4902820726357787,
      "train_acc": 0.7996434143080009,
      "train_f1": 0.0,
      "is_personalized": true,
      "variant": "personal"
    },
    {
      "method": "ditto_concat_personal",
      "scenario": "FR_S0_congruent_iid",
      "seed": 11,
      "round": 4,
      "loss": 0.4558049945952533,
      "auroc": 0.8753781344032097,
      "auprc": 0.6647332207830476,
      "acc": 0.8396150761828388,
      "f1": 0.6047430830039525,
      "threshold": 0.25499999999999995,
      "num_selected_clients": 10,
      "selected_clients": "0,1,2,3,4,5,6,7,8,9",
      "val_loss": 0.44905951890713564,
      "val_auroc": 0.903425,
      "val_auprc": 0.7049061058630149,
      "val_acc": 0.87,
      "val_f1": 0.656084656084656,
      "train_loss": 18.020863104748624,
      "train_auroc": 0.8268713493976418,
      "train_auprc": 0.598962321114934,
      "train_acc": 0.7996434143080009,
      "train_f1": 0.0,
      "is_personalized": true,
      "variant": "personal"
    },
    {
      "method": "ditto_concat_personal",
      "scenario": "FR_S0_congruent_iid",
      "seed": 11,
      "round": 5,
      "loss": 0.43630947139596865,
      "auroc": 0.8865055165496489,
      "auprc": 0.6914625026280028,
      "acc": 0.8564554931836408,
      "f1": 0.6133909287257019,
      "threshold": 0.25999999999999995,
      "num_selected_clients": 10,
      "selected_clients": "0,1,2,3,4,5,6,7,8,9",
      "val_loss": 0.42753454451729844,
      "val_auroc": 0.912425,
      "val_auprc": 0.7333791583977948,
      "val_acc": 0.882,
      "val_f1": 0.6740331491712708,
      "train_loss": 20.672430629317894,
      "train_auroc": 0.8581163541135299,
      "train_auprc": 0.6649759001889934,
      "train_acc": 0.7996434143080009,
      "train_f1": 0.0,
      "is_personalized": true,
      "variant": "personal"
    },
    {
      "method": "ditto_concat_personal",
      "scenario": "FR_S0_congruent_iid",
      "seed": 11,
      "round": 6,
      "loss": 0.4172926694676346,
      "auroc": 0.8923550651955867,
      "auprc": 0.7043540788899624,
      "acc": 0.8051323175621492,
      "f1": 0.6255778120184899,
      "threshold": 0.21999999999999997,
      "num_selected_clients": 10,
      "selected_clients": "0,1,2,3,4,5,6,7,8,9",
      "val_loss": 0.4065027803854335,
      "val_auroc": 0.9161125000000001,
      "val_auprc": 0.7507386009398954,
      "val_acc": 0.846,
      "val_f1": 0.6857142857142857,
      "train_loss": 23.596791234451064,
      "train_auroc": 0.8743861582365106,
      "train_auprc": 0.710568345362573,
      "train_acc": 0.7996434143080009,
      "train_f1": 0.0,
      "is_personalized": true,
      "variant": "personal"
    },
    {
      "method": "ditto_concat_personal",
      "scenario": "FR_S0_congruent_iid",
      "seed": 11,
      "round": 7,
      "loss": 0.3987087355070598,
      "auroc": 0.8959478435305916,
      "auprc": 0.7118652862552438,
      "acc": 0.8299919807538091,
      "f1": 0.636986301369863,
      "threshold": 0.22999999999999998,
      "num_selected_clients": 10,
      "selected_clients": "0,1,2,3,4,5,6,7,8,9",
      "val_loss": 0.38600407376279167,
      "val_auroc": 0.9183499999999999,
      "val_auprc": 0.7645642559802756,
      "val_acc": 0.864,
      "val_f1": 0.6936936936936937,
      "train_loss": 26.77599322644432,
      "train_auroc": 0.8822091629374066,
      "train_auprc": 0.7233866992352908,
      "train_acc": 0.7996434143080009,
      "train_f1": 0.0,
      "is_personalized": true,
      "variant": "personal"
    },
    {
      "method": "ditto_concat_personal",
      "scenario": "FR_S0_congruent_iid",
      "seed": 11,
      "round": 8,
      "loss": 0.3812872617127753,
      "auroc": 0.8985717151454364,
      "auprc": 0.7186191047611786,
      "acc": 0.8444266238973537,
      "f1": 0.6548042704626335,
      "threshold": 0.235,
      "num_selected_clients": 10,
      "selected_clients": "0,1,2,3,4,5,6,7,8,9",
      "val_loss": 0.366800709400244,
      "val_auroc": 0.92035,
      "val_auprc": 0.7729425576609,
      "val_acc": 0.874,
      "val_f1": 0.7069767441860465,
      "train_loss": 30.19453833749838,
      "train_auroc": 0.8865877713813408,
      "train_auprc": 0.7339562040775991,
      "train_acc": 0.8000891464229998,
      "train_f1": 0.0043985432886703224,
      "is_personalized": true,
      "variant": "personal"
    },
    {
      "method": "ditto_concat_personal",
      "scenario": "FR_S0_congruent_iid",
      "seed": 11,
      "round": 9,
      "loss": 0.36478488594190955,
      "auroc": 0.9014483450351053,
      "auprc": 0.7251424836342553,
      "acc": 0.8524458700882117,
      "f1": 0.6617647058823529,
      "threshold": 0.245,
      "num_selected_clients": 10,
      "selected_clients": "0,1,2,3,4,5,6,7,8,9",
      "val_loss": 0.3488578397177564,
      "val_auroc": 0.9216624999999999,
      "val_auprc": 0.778346302884901,
      "val_acc": 0.878,
      "val_f1": 0.7109004739336493,
      "train_loss": 33.85386548340918,
      "train_auroc": 0.8946930994178963,
      "train_auprc": 0.7514632212878983,
      "train_acc": 0.8098952529529753,
      "train_f1": 0.09864750598657873,
      "is_personalized": true,
      "variant": "personal"
    },
    {
      "method": "ditto_concat_personal",
      "scenario": "FR_S0_congruent_iid",
      "seed": 11,
      "round": 10,
      "loss": 0.3508780470901076,
      "auroc": 0.9038676028084253,
      "auprc": 0.731505854961461,
      "acc": 0.8476343223736968,
      "f1": 0.652014652014652,
      "threshold": 0.24999999999999994,
      "num_selected_clients": 10,
      "selected_clients": "0,1,2,3,4,5,6,7,8,9",
      "val_loss": 0.3337359683199618,
      "val_auroc": 0.923275,
      "val_auprc": 0.7848408337718974,
      "val_acc": 0.878,
      "val_f1": 0.7136150234741784,
      "train_loss": 37.732732822986975,
      "train_auroc": 0.8976137444475449,
      "train_auprc": 0.7606227497881671,
      "train_acc": 0.822821484287943,
      "train_f1": 0.20979105291071323,
      "is_personalized": true,
      "variant": "personal"
    },
    {
      "method": "ditto_concat_personal",
      "scenario": "FR_S0_congruent_iid",
      "seed": 11,
      "round": 11,
      "loss": 0.33825404058771225,
      "auroc": 0.9055727181544634,
      "auprc": 0.7357497572567576,
      "acc": 0.8460304731355253,
      "f1": 0.6496350364963503,
      "threshold": 0.25499999999999995,
      "num_selected_clients": 10,
      "selected_clients": "0,1,2,3,4,5,6,7,8,9",
      "val_loss": 0.3200074252620176,
      "val_auroc": 0.9245,
      "val_auprc": 0.789170741233914,
      "val_acc": 0.878,
      "val_f1": 0.7136150234741784,
      "train_loss": 41.868902898881544,
      "train_auroc": 0.8980529041516652,
      "train_auprc": 0.7656133147107671,
      "train_acc": 0.8535770002228661,
      "train_f1": 0.4388828361960922,
      "is_personalized": true,
      "variant": "personal"
    },
    {
      "method": "ditto_concat_personal",
      "scenario": "FR_S0_congruent_iid",
      "seed": 11,
      "round": 12,
      "loss": 0.3267047607481551,
      "auroc": 0.9074884653961884,
      "auprc": 0.739720427223464,
      "acc": 0.842822774659182,
      "f1": 0.6585365853658537,
      "threshold": 0.245,
      "num_selected_clients": 10,
      "selected_clients": "0,1,2,3,4,5,6,7,8,9",
      "val_loss": 0.30753882048232617,
      "val_auroc": 0.925825,
      "val_auprc": 0.79405189733498,
      "val_acc": 0.874,
      "val_f1": 0.7149321266968326,
      "train_loss": 46.26387264225354,
      "train_auroc": 0.9013068851762853,
      "train_auprc": 0.7708853783538803,
      "train_acc": 0.8633831067528416,
      "train_f1": 0.5019694458727004,
      "is_personalized": true,
      "variant": "personal"
    },
    {
      "method": "ditto_concat_personal",
      "scenario": "FR_S0_congruent_iid",
      "seed": 11,
      "round": 13,
      "loss": 0.3177182536556469,
      "auroc": 0.909346038114343,
      "auprc": 0.7445026728138814,
      "acc": 0.8396150761828388,
      "f1": 0.6655518394648829,
      "threshold": 0.22999999999999998,
      "num_selected_clients": 10,
      "selected_clients": "0,1,2,3,4,5,6,7,8,9",
      "val_loss": 0.2975462034493351,
      "val_auroc": 0.92745,
      "val_auprc": 0.7986607365300774,
      "val_acc": 0.87,
      "val_f1": 0.723404255319149,
      "train_loss": 50.92309729931268,
      "train_auroc": 0.9054248194301903,
      "train_auprc": 0.7811330105982405,
      "train_acc": 0.8736349453978159,
      "train_f1": 0.5649397784962855,
      "is_personalized": true,
      "variant": "personal"
    },
    {
      "method": "ditto_concat_personal",
      "scenario": "FR_S0_congruent_iid",
      "seed": 11,
      "round": 14,
      "loss": 0.309337896648014,
      "auroc": 0.9109287863590771,
      "auprc": 0.7478822598322397,
      "acc": 0.8380112269446672,
      "f1": 0.6688524590163935,
      "threshold": 0.22499999999999998,
      "num_selected_clients": 10,
      "selected_clients": "0,1,2,3,4,5,6,7,8,9",
      "val_loss": 0.2883313425027088,
      "val_auroc": 0.9283874999999999,
      "val_auprc": 0.8015057312969379,
      "val_acc": 0.874,
      "val_f1": 0.7341772151898734,
      "train_loss": 55.814280284442056,
      "train_auroc": 0.9082667531694,
      "train_auprc": 0.7825700746692417,
      "train_acc": 0.8823267216402941,
      "train_f1": 0.6152157381472071,
      "is_personalized": true,
      "variant": "personal"
    },
    {
      "method": "ditto_concat_personal",
      "scenario": "FR_S0_congruent_iid",
      "seed": 11,
      "round": 15,
      "loss": 0.3031324598480393,
      "auroc": 0.9121685055165496,
      "auprc": 0.7512935672225324,
      "acc": 0.8396150761828388,
      "f1": 0.66996699669967,
      "threshold": 0.22499999999999998,
      "num_selected_clients": 10,
      "selected_clients": "0,1,2,3,4,5,6,7,8,9",
      "val_loss": 0.28149521186287985,
      "val_auroc": 0.9295500000000001,
      "val_auprc": 0.8043072532799788,
      "val_acc": 0.874,
      "val_f1": 0.7341772151898734,
      "train_loss": 60.926916005963704,
      "train_auroc": 0.9128412869914493,
      "train_auprc": 0.7900868167003077,
      "train_acc": 0.8921328281702696,
      "train_f1": 0.66194043665436,
      "is_personalized": true,
      "variant": "personal"
    },
    {
      "method": "ditto_concat_personal",
      "scenario": "FR_S0_congruent_iid",
      "seed": 11,
      "round": 16,
      "loss": 0.2974891869152254,
      "auroc": 0.9136589769307923,
      "auprc": 0.7549908254976109,
      "acc": 0.842822774659182,
      "f1": 0.6765676567656765,
      "threshold": 0.22999999999999998,
      "num_selected_clients": 10,
      "selected_clients": "0,1,2,3,4,5,6,7,8,9",
      "val_loss": 0.2754718634220962,
      "val_auroc": 0.9297625,
      "val_auprc": 0.8058492126860108,
      "val_acc": 0.874,
      "val_f1": 0.7341772151898734,
      "train_loss": 66.27720977353019,
      "train_auroc": 0.9145761230192109,
      "train_auprc": 0.7909834385882928,
      "train_acc": 0.8903498997102741,
      "train_f1": 0.6601174494141097,
      "is_personalized": true,
      "variant": "personal"
    },
    {
      "method": "ditto_concat_personal",
      "scenario": "FR_S0_congruent_iid",
      "seed": 11,
      "round": 17,
      "loss": 0.2930949603312065,
      "auroc": 0.9148425275827483,
      "auprc": 0.7586725021482841,
      "acc": 0.8484362469927826,
      "f1": 0.6666666666666666,
      "threshold": 0.24999999999999994,
      "num_selected_clients": 10,
      "selected_clients": "0,1,2,3,4,5,6,7,8,9",
      "val_loss": 0.27096552668847906,
      "val_auroc": 0.9306750000000001,
      "val_auprc": 0.8078792626215751,
      "val_acc": 0.882,
      "val_f1": 0.7354260089686099,
      "train_loss": 71.8427528362644,
      "train_auroc": 0.9151093677298665,
      "train_auprc": 0.7899107949387401,
      "train_acc": 0.8916870960552707,
      "train_f1": 0.6695675109035206,
      "is_personalized": true,
      "variant": "personal"
    },
    {
      "method": "ditto_concat_personal",
      "scenario": "FR_S0_congruent_iid",
      "seed": 11,
      "round": 18,
      "loss": 0.2890578630403974,
      "auroc": 0.9160260782347039,
      "auprc": 0.7615765681285062,
      "acc": 0.8540497193263833,
      "f1": 0.675,
      "threshold": 0.25499999999999995,
      "num_selected_clients": 10,
      "selected_clients": "0,1,2,3,4,5,6,7,8,9",
      "val_loss": 0.26612406062559546,
      "val_auroc": 0.931675,
      "val_auprc": 0.8102662834991304,
      "val_acc": 0.884,
      "val_f1": 0.7410714285714286,
      "train_loss": 77.6333537683047,
      "train_auroc": 0.9203502616942796,
      "train_auprc": 0.8075553028026998,
      "train_acc": 0.8950300869177624,
      "train_f1": 0.6864472434156953,
      "is_personalized": true,
      "variant": "personal"
    },
    {
      "method": "ditto_concat_personal",
      "scenario": "FR_S0_congruent_iid",
      "seed": 11,
      "round": 19,
      "loss": 0.28595262487775097,
      "auroc": 0.917147442326981,
      "auprc": 0.7642355590656017,
      "acc": 0.8500400962309543,
      "f1": 0.6792452830188679,
      "threshold": 0.24,
      "num_selected_clients": 10,
      "selected_clients": "0,1,2,3,4,5,6,7,8,9",
      "val_loss": 0.26286799099247277,
      "val_auroc": 0.9321999999999999,
      "val_auprc": 0.8106882709797453,
      "val_acc": 0.88,
      "val_f1": 0.7391304347826086,
      "train_loss": 83.66699058408591,
      "train_auroc": 0.9213886925282586,
      "train_auprc": 0.8076841987272362,
      "train_acc": 0.8943614887452641,
      "train_f1": 0.6832083286400013,
      "is_personalized": true,
      "variant": "personal"
    },
    {
      "method": "ditto_concat_personal",
      "scenario": "FR_S0_congruent_iid",
      "seed": 11,
      "round": 20,
      "loss": 0.2837957964361979,
      "auroc": 0.9177171514543631,
      "auprc": 0.7659658063849204,
      "acc": 0.8556535685645549,
      "f1": 0.6853146853146853,
      "threshold": 0.245,
      "num_selected_clients": 10,
      "selected_clients": "0,1,2,3,4,5,6,7,8,9",
      "val_loss": 0.2600384337062318,
      "val_auroc": 0.9332125,
      "val_auprc": 0.8135159629524529,
      "val_acc": 0.886,
      "val_f1": 0.748898678414097,
      "train_loss": 89.93377372983147,
      "train_auroc": 0.9239068110748998,
      "train_auprc": 0.8154680513539878,
      "train_acc": 0.8977044796077558,
      "train_f1": 0.6986706555174141,
      "is_personalized": true,
      "variant": "personal"
    },
    {
      "method": "ditto_concat_personal",
      "scenario": "FR_S0_congruent_iid",
      "seed": 11,
      "round": 21,
      "loss": 0.28126356146058484,
      "auroc": 0.918754262788365,
      "auprc": 0.7677967943964892,
      "acc": 0.859663191659984,
      "f1": 0.6835443037974683,
      "threshold": 0.26499999999999996,
      "num_selected_clients": 10,
      "selected_clients": "0,1,2,3,4,5,6,7,8,9",
      "val_loss": 0.25737063425968143,
      "val_auroc": 0.9339875,
      "val_auprc": 0.8154562092626468,
      "val_acc": 0.892,
      "val_f1": 0.7522935779816514,
      "train_loss": 96.41008670382652,
      "train_auroc": 0.9263643596268168,
      "train_auprc": 0.821464429427875,
      "train_acc": 0.8979273456652552,
      "train_f1": 0.6984338516050125,
      "is_personalized": true,
      "variant": "personal"
    },
    {
      "method": "ditto_concat_personal",
      "scenario": "FR_S0_congruent_iid",
      "seed": 11,
      "round": 22,
      "loss": 0.27948864835593,
      "auroc": 0.9194904714142427,
      "auprc": 0.770181232871253,
      "acc": 0.863672814755413,
      "f1": 0.6897810218978102,
      "threshold": 0.27499999999999997,
      "num_selected_clients": 10,
      "selected_clients": "0,1,2,3,4,5,6,7,8,9",
      "val_loss": 0.25547526553100003,
      "val_auroc": 0.9343,
      "val_auprc": 0.8160764524749082,
      "val_acc": 0.894,
      "val_f1": 0.7534883720930232,
      "train_loss": 103.1260660718591,
      "train_auroc": 0.926753462431751,
      "train_auprc": 0.8182609076969656,
      "train_acc": 0.8983730777802541,
      "train_f1": 0.7054826748301809,
      "is_personalized": true,
      "variant": "personal"
    },
    {
      "method": "ditto_concat_personal",
      "scenario": "FR_S0_congruent_iid",
      "seed": 11,
      "round": 23,
      "loss": 0.27736303050443634,
      "auroc": 0.9205897693079236,
      "auprc": 0.7735889944365331,
      "acc": 0.8612670408981555,
      "f1": 0.6894075403949731,
      "threshold": 0.26999999999999996,
      "num_selected_clients": 10,
      "selected_clients": "0,1,2,3,4,5,6,7,8,9",
      "val_loss": 0.25377517437282643,
      "val_auroc": 0.93455,
      "val_auprc": 0.8172905829818348,
      "val_acc": 0.892,
      "val_f1": 0.7545454545454545,
      "train_loss": 110.08425664125956,
      "train_auroc": 0.9282079483964566,
      "train_auprc": 0.8236072191631936,
      "train_acc": 0.9001560062402496,
      "train_f1": 0.7094398039394224,
      "is_personalized": true,
      "variant": "personal"
    },
    {
      "method": "ditto_concat_personal",
      "scenario": "FR_S0_congruent_iid",
      "seed": 11,
      "round": 24,
      "loss": 0.2761434234415408,
      "auroc": 0.9210130391173521,
      "auprc": 0.7738824009400477,
      "acc": 0.863672814755413,
      "f1": 0.6931407942238267,
      "threshold": 0.27499999999999997,
      "num_selected_clients": 10,
      "selected_clients": "0,1,2,3,4,5,6,7,8,9",
      "val_loss": 0.25213260491919043,
      "val_auroc": 0.9349375,
      "val_auprc": 0.817382568895226,
      "val_acc": 0.9,
      "val_f1": 0.7685185185185185,
      "train_loss": 117.28183592712797,
      "train_auroc": 0.9303608075370131,
      "train_auprc": 0.8292278217242789,
      "train_acc": 0.9021618007577445,
      "train_f1": 0.7195305086549934,
      "is_personalized": true,
      "variant": "personal"
    },
    {
      "method": "ditto_concat_personal",
      "scenario": "FR_S0_congruent_iid",
      "seed": 11,
      "round": 25,
      "loss": 0.2745888284208534,
      "auroc": 0.9216489468405213,
      "auprc": 0.776416696011732,
      "acc": 0.8644747393744988,
      "f1": 0.6932849364791288,
      "threshold": 0.26999999999999996,
      "num_selected_clients": 10,
      "selected_clients": "0,1,2,3,4,5,6,7,8,9",
      "val_loss": 0.2505976971160426,
      "val_auroc": 0.935675,
      "val_auprc": 0.8206165278153743,
      "val_acc": 0.9,
      "val_f1": 0.7685185185185185,
      "train_loss": 124.73133735580224,
      "train_auroc": 0.9310078831810334,
      "train_auprc": 0.8317191836462721,
      "train_acc": 0.9052819255627368,
      "train_f1": 0.7329890766149321,
      "is_personalized": true,
      "variant": "personal"
    },
    {
      "method": "ditto_concat_personal",
      "scenario": "FR_S0_congruent_iid",
      "seed": 11,
      "round": 26,
      "loss": 0.2735758974520327,
      "auroc": 0.9221805416248745,
      "auprc": 0.7785708112430244,
      "acc": 0.8612670408981555,
      "f1": 0.6882882882882883,
      "threshold": 0.26499999999999996,
      "num_selected_clients": 10,
      "selected_clients": "0,1,2,3,4,5,6,7,8,9",
      "val_loss": 0.249125717170509,
      "val_auroc": 0.9358625,
      "val_auprc": 0.8210112861924159,
      "val_acc": 0.9,
      "val_f1": 0.7685185185185185,
      "train_loss": 132.4445813023648,
      "train_auroc": 0.9318766504112564,
      "train_auprc": 0.8307615278623796,
      "train_acc": 0.9050590595052374,
      "train_f1": 0.7289280165224263,
      "is_personalized": true,
      "variant": "personal"
    },
    {
      "method": "ditto_concat_personal",
      "scenario": "FR_S0_congruent_iid",
      "seed": 11,
      "round": 27,
      "loss": 0.2724664010628598,
      "auroc": 0.9225877632898696,
      "auprc": 0.7798228654663864,
      "acc": 0.8612670408981555,
      "f1": 0.6860254083484574,
      "threshold": 0.25999999999999995,
      "num_selected_clients": 10,
      "selected_clients": "0,1,2,3,4,5,6,7,8,9",
      "val_loss": 0.24794654250644033,
      "val_auroc": 0.9359124999999999,
      "val_auprc": 0.8205925361703282,
      "val_acc": 0.9,
      "val_f1": 0.7685185185185185,
      "train_loss": 140.36954717123882,
      "train_auroc": 0.9366669227645023,
      "train_auprc": 0.8408773457709,
      "train_acc": 0.9070648540227323,
      "train_f1": 0.7344281054487191,
      "is_personalized": true,
      "variant": "personal"
    },
    {
      "method": "ditto_concat_personal",
      "scenario": "FR_S0_congruent_iid",
      "seed": 11,
      "round": 28,
      "loss": 0.2715217485999303,
      "auroc": 0.9230892678034102,
      "auprc": 0.7816076743321225,
      "acc": 0.8652766639935846,
      "f1": 0.6900369003690037,
      "threshold": 0.26499999999999996,
      "num_selected_clients": 10,
      "selected_clients": "0,1,2,3,4,5,6,7,8,9",
      "val_loss": 0.24753766676853634,
      "val_auroc": 0.9360499999999999,
      "val_auprc": 0.8213382004421923,
      "val_acc": 0.902,
      "val_f1": 0.7699530516431925,
      "train_loss": 148.5247598371342,
      "train_auroc": 0.9367183186923189,
      "train_auprc": 0.8421397182355775,
      "train_acc": 0.9066191219077334,
      "train_f1": 0.7355774150567177,
      "is_personalized": true,
      "variant": "personal"
    },
    {
      "method": "ditto_concat_personal",
      "scenario": "FR_S0_congruent_iid",
      "seed": 11,
      "round": 29,
      "loss": 0.270278278049276,
      "auroc": 0.9235205616850551,
      "auprc": 0.7834948614639979,
      "acc": 0.8660785886126704,
      "f1": 0.6935779816513762,
      "threshold": 0.26999999999999996,
      "num_selected_clients": 10,
      "selected_clients": "0,1,2,3,4,5,6,7,8,9",
      "val_loss": 0.24646536795812019,
      "val_auroc": 0.9363250000000001,
      "val_auprc": 0.8238790977952156,
      "val_acc": 0.902,
      "val_f1": 0.7699530516431925,
      "train_loss": 156.9157087229556,
      "train_auroc": 0.9383214164143547,
      "train_auprc": 0.8432981246326801,
      "train_acc": 0.9090706485402273,
      "train_f1": 0.7430612393019034,
      "is_personalized": true,
      "variant": "personal"
    },
    {
      "method": "ditto_concat_personal",
      "scenario": "FR_S0_congruent_iid",
      "seed": 11,
      "round": 30,
      "loss": 0.269869432465908,
      "auroc": 0.9238054162487461,
      "auprc": 0.7839529832077143,
      "acc": 0.8700882117080995,
      "f1": 0.6988847583643123,
      "threshold": 0.27499999999999997,
      "num_selected_clients": 10,
      "selected_clients": "0,1,2,3,4,5,6,7,8,9",
      "val_loss": 0.24538207984692254,
      "val_auroc": 0.93675,
      "val_auprc": 0.8227815400815922,
      "val_acc": 0.902,
      "val_f1": 0.7699530516431925,
      "train_loss": 165.55454362206558,
      "train_auroc": 0.9390421253240232,
      "train_auprc": 0.8465947498079687,
      "train_acc": 0.9092935145977268,
      "train_f1": 0.7456963780989777,
      "is_personalized": true,
      "variant": "personal"
    },
    {
      "method": "ditto_concat_personal",
      "scenario": "FR_S0_congruent_iid",
      "seed": 11,
      "round": 31,
      "loss": 0.26906676485529524,
      "auroc": 0.9244794383149448,
      "auprc": 0.7870732523529311,
      "acc": 0.8684843624699278,
      "f1": 0.6951672862453532,
      "threshold": 0.3,
      "num_selected_clients": 10,
      "selected_clients": "0,1,2,3,4,5,6,7,8,9",
      "val_loss": 0.24480706806812802,
      "val_auroc": 0.9372,
      "val_auprc": 0.8261399196780789,
      "val_acc": 0.9,
      "val_f1": 0.7641509433962265,
      "train_loss": 174.4436032461222,
      "train_auroc": 0.9393862821105211,
      "train_auprc": 0.8477556576481909,
      "train_acc": 0.9108535770002228,
      "train_f1": 0.752056810440666,
      "is_personalized": true,
      "variant": "personal"
    },
    {
      "method": "ditto_concat_personal",
      "scenario": "FR_S0_congruent_iid",
      "seed": 11,
      "round": 32,
      "loss": 0.26892032176050473,
      "auroc": 0.9243309929789366,
      "auprc": 0.7857509400056081,
      "acc": 0.8684843624699278,
      "f1": 0.6985294117647058,
      "threshold": 0.26499999999999996,
      "num_selected_clients": 10,
      "selected_clients": "0,1,2,3,4,5,6,7,8,9",
      "val_loss": 0.2449556506454336,
      "val_auroc": 0.937325,
      "val_auprc": 0.826012867788878,
      "val_acc": 0.9,
      "val_f1": 0.7663551401869159,
      "train_loss": 183.5732984243163,
      "train_auroc": 0.9411491983579671,
      "train_auprc": 0.8535048431753899,
      "train_acc": 0.9108535770002228,
      "train_f1": 0.7476690622302953,
      "is_personalized": true,
      "variant": "personal"
    },
    {
      "method": "ditto_concat_personal",
      "scenario": "FR_S0_congruent_iid",
      "seed": 11,
      "round": 33,
      "loss": 0.2682616927475136,
      "auroc": 0.9248324974924774,
      "auprc": 0.7877044940441961,
      "acc": 0.8692862870890137,
      "f1": 0.7009174311926606,
      "threshold": 0.25999999999999995,
      "num_selected_clients": 10,
      "selected_clients": "0,1,2,3,4,5,6,7,8,9",
      "val_loss": 0.24439074349859294,
      "val_auroc": 0.937475,
      "val_auprc": 0.826121999693456,
      "val_acc": 0.898,
      "val_f1": 0.7627906976744186,
      "train_loss": 192.94443312896396,
      "train_auroc": 0.9442640691184417,
      "train_auprc": 0.857027735676514,
      "train_acc": 0.910407844885224,
      "train_f1": 0.750399204861444,
      "is_personalized": true,
      "variant": "personal"
    },
    {
      "method": "ditto_concat_personal",
      "scenario": "FR_S0_congruent_iid",
      "seed": 11,
      "round": 34,
      "loss": 0.26796665620267235,
      "auroc": 0.9250070210631894,
      "auprc": 0.7884942021634425,
      "acc": 0.8684843624699278,
      "f1": 0.7007299270072993,
      "threshold": 0.26499999999999996,
      "num_selected_clients": 10,
      "selected_clients": "0,1,2,3,4,5,6,7,8,9",
      "val_loss": 0.24441197573493695,
      "val_auroc": 0.93715,
      "val_auprc": 0.8246502961807937,
      "val_acc": 0.898,
      "val_f1": 0.7627906976744186,
      "train_loss": 202.5667300465539,
      "train_auroc": 0.9450819510252455,
      "train_auprc": 0.8590181864673786,
      "train_acc": 0.9146422999777134,
      "train_f1": 0.7616658043446036,
      "is_personalized": true,
      "variant": "personal"
    },
    {
      "method": "ditto_concat_personal",
      "scenario": "FR_S0_congruent_iid",
      "seed": 11,
      "round": 35,
      "loss": 0.2671435832009457,
      "auroc": 0.9252236710130392,
      "auprc": 0.7886788469165048,
      "acc": 0.871692060946271,
      "f1": 0.6992481203007519,
      "threshold": 0.30499999999999994,
      "num_selected_clients": 10,
      "selected_clients": "0,1,2,3,4,5,6,7,8,9",
      "val_loss": 0.24344577149522986,
      "val_auroc": 0.93715,
      "val_auprc": 0.8249235347416805,
      "val_acc": 0.9,
      "val_f1": 0.7619047619047619,
      "train_loss": 212.4338711631678,
      "train_auroc": 0.9470447511478863,
      "train_auprc": 0.8622561608989021,
      "train_acc": 0.9146422999777134,
      "train_f1": 0.7623919958927551,
      "is_personalized": true,
      "variant": "personal"
    },
    {
      "method": "ditto_concat_personal",
      "scenario": "FR_S0_congruent_iid",
      "seed": 11,
      "round": 36,
      "loss": 0.2673793325670046,
      "auroc": 0.9252557673019058,
      "auprc": 0.7876624826614553,
      "acc": 0.8684843624699278,
      "f1": 0.6985294117647058,
      "threshold": 0.25499999999999995,
      "num_selected_clients": 10,
      "selected_clients": "0,1,2,3,4,5,6,7,8,9",
      "val_loss": 0.243743054749799,
      "val_auroc": 0.93735,
      "val_auprc": 0.8244780529458091,
      "val_acc": 0.898,
      "val_f1": 0.7627906976744186,
      "train_loss": 222.55977786833336,
      "train_auroc": 0.9461554558920138,
      "train_auprc": 0.8606308388363698,
      "train_acc": 0.9130822375752173,
      "train_f1": 0.7616267240231834,
      "is_personalized": true,
      "variant": "personal"
    },
    {
      "method": "ditto_concat_personal",
      "scenario": "FR_S0_congruent_iid",
      "seed": 11,
      "round": 37,
      "loss": 0.26539600947550124,
      "auroc": 0.9260220661985957,
      "auprc": 0.7919444784945178,
      "acc": 0.8732959101844426,
      "f1": 0.7106227106227107,
      "threshold": 0.285,
      "num_selected_clients": 10,
      "selected_clients": "0,1,2,3,4,5,6,7,8,9",
      "val_loss": 0.24320634134143795,
      "val_auroc": 0.9366875,
      "val_auprc": 0.8252729321513169,
      "val_acc": 0.894,
      "val_f1": 0.7534883720930232,
      "train_loss": 232.90638202406234,
      "train_auroc": 0.9465755266906353,
      "train_auprc": 0.8655187627490398,
      "train_acc": 0.9155337642077112,
      "train_f1": 0.7670775675267251,
      "is_personalized": true,
      "variant": "personal"
    },
    {
      "method": "ditto_concat_personal",
      "scenario": "FR_S0_congruent_iid",
      "seed": 11,
      "round": 38,
      "loss": 0.266270944447247,
      "auroc": 0.9256228686058174,
      "auprc": 0.7893509770765741,
      "acc": 0.8708901363271853,
      "f1": 0.7067395264116576,
      "threshold": 0.26499999999999996,
      "num_selected_clients": 10,
      "selected_clients": "0,1,2,3,4,5,6,7,8,9",
      "val_loss": 0.24336143682481293,
      "val_auroc": 0.9370875,
      "val_auprc": 0.8247335629906436,
      "val_acc": 0.898,
      "val_f1": 0.7627906976744186,
      "train_loss": 243.50878797683734,
      "train_auroc": 0.9481276077310109,
      "train_auprc": 0.8636657317162078,
      "train_acc": 0.9170938266102072,
      "train_f1": 0.7708162934602698,
      "is_personalized": true,
      "variant": "personal"
    },
    {
      "method": "ditto_concat_personal",
      "scenario": "FR_S0_congruent_iid",
      "seed": 11,
      "round": 39,
      "loss": 0.2652767936931712,
      "auroc": 0.9258736208625877,
      "auprc": 0.7923576497681794,
      "acc": 0.871692060946271,
      "f1": 0.708029197080292,
      "threshold": 0.27499999999999997,
      "num_selected_clients": 10,
      "selected_clients": "0,1,2,3,4,5,6,7,8,9",
      "val_loss": 0.24203947340428295,
      "val_auroc": 0.937475,
      "val_auprc": 0.8266032362386248,
      "val_acc": 0.894,
      "val_f1": 0.7557603686635944,
      "train_loss": 254.33048652290157,
      "train_auroc": 0.9480862839961283,
      "train_auprc": 0.865775031007491,
      "train_acc": 0.9195453532427011,
      "train_f1": 0.7768707396512065,
      "is_personalized": true,
      "variant": "personal"
    },
    {
      "method": "ditto_concat_personal",
      "scenario": "FR_S0_congruent_iid",
      "seed": 11,
      "round": 40,
      "loss": 0.2650411807845247,
      "auroc": 0.9260040120361084,
      "auprc": 0.7909661997116069,
      "acc": 0.8748997594226142,
      "f1": 0.7100371747211895,
      "threshold": 0.27999999999999997,
      "num_selected_clients": 10,
      "selected_clients": "0,1,2,3,4,5,6,7,8,9",
      "val_loss": 0.2419888123614193,
      "val_auroc": 0.9376374999999999,
      "val_auprc": 0.8249501715488977,
      "val_acc": 0.894,
      "val_f1": 0.7488151658767772,
      "train_loss": 265.3871931782113,
      "train_auroc": 0.9499686391166458,
      "train_auprc": 0.8677283247971513,
      "train_acc": 0.9153108981502117,
      "train_f1": 0.766417869921289,
      "is_personalized": true,
      "variant": "personal"
    },
    {
      "method": "ditto_concat_personal",
      "scenario": "FR_S0_congruent_iid",
      "seed": 11,
      "round": 41,
      "loss": 0.2635617374075262,
      "auroc": 0.9265757271815446,
      "auprc": 0.7956358747339147,
      "acc": 0.871692060946271,
      "f1": 0.708029197080292,
      "threshold": 0.26499999999999996,
      "num_selected_clients": 10,
      "selected_clients": "0,1,2,3,4,5,6,7,8,9",
      "val_loss": 0.2413541444803324,
      "val_auroc": 0.937925,
      "val_auprc": 0.8272826753987482,
      "val_acc": 0.896,
      "val_f1": 0.7592592592592593,
      "train_loss": 276.68436621174345,
      "train_auroc": 0.951624736138085,
      "train_auprc": 0.8722737892097229,
      "train_acc": 0.9188767550702028,
      "train_f1": 0.7768840879021274,
      "is_personalized": true,
      "variant": "personal"
    },
    {
      "method": "ditto_concat_personal",
      "scenario": "FR_S0_congruent_iid",
      "seed": 11,
      "round": 42,
      "loss": 0.2643304800781158,
      "auroc": 0.926740220661986,
      "auprc": 0.7963200541937481,
      "acc": 0.871692060946271,
      "f1": 0.706959706959707,
      "threshold": 0.245,
      "num_selected_clients": 10,
      "selected_clients": "0,1,2,3,4,5,6,7,8,9",
      "val_loss": 0.2420843715063027,
      "val_auroc": 0.9380625,
      "val_auprc": 0.8280763505629909,
      "val_acc": 0.894,
      "val_f1": 0.7534883720930232,
      "train_loss": 288.2343542108776,
      "train_auroc": 0.9512951948098266,
      "train_auprc": 0.8742266043560079,
      "train_acc": 0.9215511477601961,
      "train_f1": 0.7829206285726102,
      "is_personalized": true,
      "variant": "personal"
    },
    {
      "method": "ditto_concat_personal",
      "scenario": "FR_S0_congruent_iid",
      "seed": 11,
      "round": 43,
      "loss": 0.2642414791845643,
      "auroc": 0.9264112337011033,
      "auprc": 0.7961693327482456,
      "acc": 0.871692060946271,
      "f1": 0.7058823529411765,
      "threshold": 0.27499999999999997,
      "num_selected_clients": 10,
      "selected_clients": "0,1,2,3,4,5,6,7,8,9",
      "val_loss": 0.24012483923130526,
      "val_auroc": 0.938175,
      "val_auprc": 0.8296132513949024,
      "val_acc": 0.896,
      "val_f1": 0.7570093457943925,
      "train_loss": 300.0270978338022,
      "train_auroc": 0.9524602691625035,
      "train_auprc": 0.875844285917123,
      "train_acc": 0.9204368174726989,
      "train_f1": 0.7806611921362989,
      "is_personalized": true,
      "variant": "personal"
    },
    {
      "method": "ditto_concat_personal",
      "scenario": "FR_S0_congruent_iid",
      "seed": 11,
      "round": 44,
      "loss": 0.2635214814492548,
      "auroc": 0.9266258776328987,
      "auprc": 0.7969449999968162,
      "acc": 0.8700882117080995,
      "f1": 0.7065217391304348,
      "threshold": 0.25999999999999995,
      "num_selected_clients": 10,
      "selected_clients": "0,1,2,3,4,5,6,7,8,9",
      "val_loss": 0.23987877470834315,
      "val_auroc": 0.9382999999999999,
      "val_auprc": 0.8304495137443624,
      "val_acc": 0.892,
      "val_f1": 0.7522935779816514,
      "train_loss": 312.09064922498544,
      "train_auroc": 0.9524387657228599,
      "train_auprc": 0.876569112459205,
      "train_acc": 0.9231112101626923,
      "train_f1": 0.7927612674407909,
      "is_personalized": true,
      "variant": "personal"
    },
    {
      "method": "ditto_concat_personal",
      "scenario": "FR_S0_congruent_iid",
      "seed": 11,
      "round": 45,
      "loss": 0.26440258890716095,
      "auroc": 0.9268946840521565,
      "auprc": 0.7971425582600273,
      "acc": 0.8700882117080995,
      "f1": 0.7043795620437956,
      "threshold": 0.245,
      "num_selected_clients": 10,
      "selected_clients": "0,1,2,3,4,5,6,7,8,9",
      "val_loss": 0.240293961419562,
      "val_auroc": 0.9389,
      "val_auprc": 0.8307486716542503,
      "val_acc": 0.896,
      "val_f1": 0.7592592592592593,
      "train_loss": 324.37369518267275,
      "train_auroc": 0.9538873372878008,
      "train_auprc": 0.8792387391168242,
      "train_acc": 0.9213282817026966,
      "train_f1": 0.7827372771422114,
      "is_personalized": true,
      "variant": "personal"
    },
    {
      "method": "ditto_concat_personal",
      "scenario": "FR_S0_congruent_iid",
      "seed": 11,
      "round": 46,
      "loss": 0.26405257686125216,
      "auroc": 0.9267883650952857,
      "auprc": 0.7969293131452407,
      "acc": 0.8692862870890137,
      "f1": 0.7041742286751361,
      "threshold": 0.29,
      "num_selected_clients": 10,
      "selected_clients": "0,1,2,3,4,5,6,7,8,9",
      "val_loss": 0.23920658293288183,
      "val_auroc": 0.9383125,
      "val_auprc": 0.8288229327598992,
      "val_acc": 0.892,
      "val_f1": 0.7476635514018691,
      "train_loss": 336.8783605931356,
      "train_auroc": 0.9563346660300734,
      "train_auprc": 0.8868245187325937,
      "train_acc": 0.9253398707376866,
      "train_f1": 0.795528413542635,
      "is_personalized": true,
      "variant": "personal"
    },
    {
      "method": "ditto_concat_personal",
      "scenario": "FR_S0_congruent_iid",
      "seed": 11,
      "round": 47,
      "loss": 0.2638398277146616,
      "auroc": 0.9269087261785356,
      "auprc": 0.797994212525273,
      "acc": 0.871692060946271,
      "f1": 0.7090909090909091,
      "threshold": 0.24,
      "num_selected_clients": 10,
      "selected_clients": "0,1,2,3,4,5,6,7,8,9",
      "val_loss": 0.2407228783602012,
      "val_auroc": 0.9383124999999999,
      "val_auprc": 0.8304367715038125,
      "val_acc": 0.896,
      "val_f1": 0.7592592592592593,
      "train_loss": 349.6272787013775,
      "train_auroc": 0.9549815966871248,
      "train_auprc": 0.8817602859759006,
      "train_acc": 0.9262313349676844,
      "train_f1": 0.7994995831649326,
      "is_personalized": true,
      "variant": "personal"
    },
    {
      "method": "ditto_concat_personal",
      "scenario": "FR_S0_congruent_iid",
      "seed": 11,
      "round": 48,
      "loss": 0.26317144614132704,
      "auroc": 0.9269969909729188,
      "auprc": 0.798683151562273,
      "acc": 0.8740978348035284,
      "f1": 0.707635009310987,
      "threshold": 0.285,
      "num_selected_clients": 10,
      "selected_clients": "0,1,2,3,4,5,6,7,8,9",
      "val_loss": 0.23962037382572676,
      "val_auroc": 0.93785,
      "val_auprc": 0.8300808576901229,
      "val_acc": 0.892,
      "val_f1": 0.7452830188679245,
      "train_loss": 362.61662885344106,
      "train_auroc": 0.9565548769362636,
      "train_auprc": 0.8860932772060409,
      "train_acc": 0.9235569422776911,
      "train_f1": 0.7914874151310343,
      "is_personalized": true,
      "variant": "personal"
    },
    {
      "method": "ditto_concat_personal",
      "scenario": "FR_S0_congruent_iid",
      "seed": 11,
      "round": 49,
      "loss": 0.2630750831221907,
      "auroc": 0.9269027081243731,
      "auprc": 0.7979083446355562,
      "acc": 0.871692060946271,
      "f1": 0.7101449275362319,
      "threshold": 0.25999999999999995,
      "num_selected_clients": 10,
      "selected_clients": "0,1,2,3,4,5,6,7,8,9",
      "val_loss": 0.24040918025605212,
      "val_auroc": 0.9373625,
      "val_auprc": 0.8287957090283026,
      "val_acc": 0.89,
      "val_f1": 0.7465437788018433,
      "train_loss": 375.8731109278224,
      "train_auroc": 0.9595409127952363,
      "train_auprc": 0.8896864573307367,
      "train_acc": 0.9264542010251838,
      "train_f1": 0.8004560933348618,
      "is_personalized": true,
      "variant": "personal"
    },
    {
      "method": "ditto_concat_personal",
      "scenario": "FR_S0_congruent_iid",
      "seed": 11,
      "round": 50,
      "loss": 0.2633792174718608,
      "auroc": 0.9269669007021063,
      "auprc": 0.7982460054351007,
      "acc": 0.8708901363271853,
      "f1": 0.7067395264116576,
      "threshold": 0.25499999999999995,
      "num_selected_clients": 10,
      "selected_clients": "0,1,2,3,4,5,6,7,8,9",
      "val_loss": 0.24057054271296852,
      "val_auroc": 0.9377875,
      "val_auprc": 0.8298063129653721,
      "val_acc": 0.89,
      "val_f1": 0.7465437788018433,
      "train_loss": 389.3690950598992,
      "train_auroc": 0.9560779268929833,
      "train_auprc": 0.8862550697469647,
      "train_acc": 0.9264542010251838,
      "train_f1": 0.8013503473675117,
      "is_personalized": true,
      "variant": "personal"
    },
    {
      "method": "ditto_concat_personal",
      "scenario": "FR_S0_congruent_iid",
      "seed": 11,
      "round": 51,
      "loss": 0.2632656633503647,
      "auroc": 0.9272998996990973,
      "auprc": 0.7992022582851103,
      "acc": 0.8789093825180433,
      "f1": 0.7123809523809523,
      "threshold": 0.30999999999999994,
      "num_selected_clients": 10,
      "selected_clients": "0,1,2,3,4,5,6,7,8,9",
      "val_loss": 0.24110644917486598,
      "val_auroc": 0.936925,
      "val_auprc": 0.8282467080466319,
      "val_acc": 0.892,
      "val_f1": 0.7378640776699029,
      "train_loss": 403.10831442574283,
      "train_auroc": 0.9586887877634275,
      "train_auprc": 0.8903179541584642,
      "train_acc": 0.9277913973701806,
      "train_f1": 0.8019581998749743,
      "is_personalized": true,
      "variant": "personal"
    },
    {
      "method": "ditto_concat_personal",
      "scenario": "FR_S0_congruent_iid",
      "seed": 11,
      "round": 52,
      "loss": 0.26205906640507276,
      "auroc": 0.9275145436308928,
      "auprc": 0.8014483439190938,
      "acc": 0.8740978348035284,
      "f1": 0.7150635208711433,
      "threshold": 0.25499999999999995,
      "num_selected_clients": 10,
      "selected_clients": "0,1,2,3,4,5,6,7,8,9",
      "val_loss": 0.2411252768919702,
      "val_auroc": 0.9371375000000001,
      "val_auprc": 0.8316716542878015,
      "val_acc": 0.888,
      "val_f1": 0.7407407407407407,
      "train_loss": 417.07389984827995,
      "train_auroc": 0.9579602669069643,
      "train_auprc": 0.8872413355771311,
      "train_acc": 0.92400267439269,
      "train_f1": 0.7940970986369037,
      "is_personalized": true,
      "variant": "personal"
    },
    {
      "method": "ditto_concat_personal",
      "scenario": "FR_S0_congruent_iid",
      "seed": 11,
      "round": 53,
      "loss": 0.26332745376059585,
      "auroc": 0.9272016048144434,
      "auprc": 0.7993221493903444,
      "acc": 0.8732959101844426,
      "f1": 0.7116788321167883,
      "threshold": 0.26499999999999996,
      "num_selected_clients": 10,
      "selected_clients": "0,1,2,3,4,5,6,7,8,9",
      "val_loss": 0.24071704530242324,
      "val_auroc": 0.9373250000000001,
      "val_auprc": 0.8271529746931848,
      "val_acc": 0.888,
      "val_f1": 0.7383177570093458,
      "train_loss": 431.2760460944757,
      "train_auroc": 0.9603708301350882,
      "train_auprc": 0.8968905127653752,
      "train_acc": 0.9309115221751727,
      "train_f1": 0.812494459380264,
      "is_personalized": true,
      "variant": "personal"
    },
    {
      "method": "ditto_concat_personal",
      "scenario": "FR_S0_congruent_iid",
      "seed": 11,
      "round": 54,
      "loss": 0.26280049231091074,
      "auroc": 0.9272978936810432,
      "auprc": 0.8011685592833698,
      "acc": 0.8748997594226142,
      "f1": 0.7089552238805971,
      "threshold": 0.285,
      "num_selected_clients": 10,
      "selected_clients": "0,1,2,3,4,5,6,7,8,9",
      "val_loss": 0.2404742117358773,
      "val_auroc": 0.9367874999999999,
      "val_auprc": 0.8304981465441781,
      "val_acc": 0.89,
      "val_f1": 0.7441860465116279,
      "train_loss": 445.71406701787004,
      "train_auroc": 0.9620286085226991,
      "train_auprc": 0.8959631911427542,
      "train_acc": 0.9295743258301761,
      "train_f1": 0.8078758804595669,
      "is_personalized": true,
      "variant": "personal"
    },
    {
      "method": "ditto_concat_personal",
      "scenario": "FR_S0_congruent_iid",
      "seed": 11,
      "round": 55,
      "loss": 0.262925810805318,
      "auroc": 0.9276970912738215,
      "auprc": 0.801697186057272,
      "acc": 0.8724939855653568,
      "f1": 0.7155635062611807,
      "threshold": 0.24,
      "num_selected_clients": 10,
      "selected_clients": "0,1,2,3,4,5,6,7,8,9",
      "val_loss": 0.24145596569628539,
      "val_auroc": 0.937125,
      "val_auprc": 0.8305371433089572,
      "val_acc": 0.886,
      "val_f1": 0.7397260273972602,
      "train_loss": 460.4107091961923,
      "train_auroc": 0.9604583722649113,
      "train_auprc": 0.8917174952616107,
      "train_acc": 0.9257856028526855,
      "train_f1": 0.8013895149940112,
      "is_personalized": true,
      "variant": "personal"
    },
    {
      "method": "ditto_concat_personal",
      "scenario": "FR_S0_congruent_iid",
      "seed": 11,
      "round": 56,
      "loss": 0.2613970239348014,
      "auroc": 0.9281083249749247,
      "auprc": 0.8027051514482388,
      "acc": 0.8692862870890137,
      "f1": 0.7094474153297683,
      "threshold": 0.24999999999999994,
      "num_selected_clients": 10,
      "selected_clients": "0,1,2,3,4,5,6,7,8,9",
      "val_loss": 0.23915104001506257,
      "val_auroc": 0.9379124999999999,
      "val_auprc": 0.8332900049090574,
      "val_acc": 0.888,
      "val_f1": 0.7431192660550459,
      "train_loss": 475.32478109350814,
      "train_auroc": 0.9636299080932157,
      "train_auprc": 0.9028405989121537,
      "train_acc": 0.9313572542901716,
      "train_f1": 0.814298064872068,
      "is_personalized": true,
      "variant": "personal"
    },
    {
      "method": "ditto_concat_personal",
      "scenario": "FR_S0_congruent_iid",
      "seed": 11,
      "round": 57,
      "loss": 0.2628120355604986,
      "auroc": 0.9279799398194583,
      "auprc": 0.8019783117923188,
      "acc": 0.8893344025661588,
      "f1": 0.7076271186440678,
      "threshold": 0.39499999999999996,
      "num_selected_clients": 10,
      "selected_clients": "0,1,2,3,4,5,6,7,8,9",
      "val_loss": 0.2415299811891382,
      "val_auroc": 0.937675,
      "val_auprc": 0.8299148643423566,
      "val_acc": 0.9,
      "val_f1": 0.7340425531914894,
      "train_loss": 490.49831212653544,
      "train_auroc": 0.9627896579163885,
      "train_auprc": 0.9002326467729573,
      "train_acc": 0.92801426342768,
      "train_f1": 0.8066158896094401,
      "is_personalized": true,
      "variant": "personal"
    },
    {
      "method": "ditto_concat_personal",
      "scenario": "FR_S0_congruent_iid",
      "seed": 11,
      "round": 58,
      "loss": 0.26216863583651895,
      "auroc": 0.9279458375125376,
      "auprc": 0.8024614748873276,
      "acc": 0.867682437850842,
      "f1": 0.7079646017699115,
      "threshold": 0.245,
      "num_selected_clients": 10,
      "selected_clients": "0,1,2,3,4,5,6,7,8,9",
      "val_loss": 0.24149842663700535,
      "val_auroc": 0.9366,
      "val_auprc": 0.8291522563187947,
      "val_acc": 0.884,
      "val_f1": 0.7363636363636363,
      "train_loss": 505.9081288519005,
      "train_auroc": 0.96299244358492,
      "train_auprc": 0.9006734645215023,
      "train_acc": 0.9309115221751727,
      "train_f1": 0.8129886725449685,
      "is_personalized": true,
      "variant": "personal"
    },
    {
      "method": "ditto_concat_personal",
      "scenario": "FR_S0_congruent_iid",
      "seed": 11,
      "round": 59,
      "loss": 0.2627184892338418,
      "auroc": 0.9279518555667001,
      "auprc": 0.8010322395771485,
      "acc": 0.8901363271852446,
      "f1": 0.7115789473684211,
      "threshold": 0.43499999999999994,
      "num_selected_clients": 10,
      "selected_clients": "0,1,2,3,4,5,6,7,8,9",
      "val_loss": 0.24154417350705307,
      "val_auroc": 0.93715,
      "val_auprc": 0.8266313820228357,
      "val_acc": 0.9,
      "val_f1": 0.7340425531914894,
      "train_loss": 521.5574470462208,
      "train_auroc": 0.963551079072026,
      "train_auprc": 0.9007864491153307,
      "train_acc": 0.9289057276576778,
      "train_f1": 0.8088056623386144,
      "is_personalized": true,
      "variant": "personal"
    },
    {
      "method": "ditto_concat_personal",
      "scenario": "FR_S0_congruent_iid",
      "seed": 11,
      "round": 60,
      "loss": 0.26328714672944575,
      "auroc": 0.9276990972918756,
      "auprc": 0.8027338157053486,
      "acc": 0.8853247794707297,
      "f1": 0.7063655030800822,
      "threshold": 0.3999999999999999,
      "num_selected_clients": 10,
      "selected_clients": "0,1,2,3,4,5,6,7,8,9",
      "val_loss": 0.24147824622393377,
      "val_auroc": 0.9365625000000001,
      "val_auprc": 0.8307874041411994,
      "val_acc": 0.898,
      "val_f1": 0.7329842931937173,
      "train_loss": 537.4614046966947,
      "train_auroc": 0.9646158363938391,
      "train_auprc": 0.9024504592431468,
      "train_acc": 0.930020057945175,
      "train_f1": 0.809197438545081,
      "is_personalized": true,
      "variant": "personal"
    },
    {
      "method": "ditto_concat_personal",
      "scenario": "FR_S0_congruent_iid",
      "seed": 11,
      "round": 61,
      "loss": 0.2614033603606088,
      "auroc": 0.9276068204613841,
      "auprc": 0.8053312438960004,
      "acc": 0.8740978348035284,
      "f1": 0.7097966728280961,
      "threshold": 0.29,
      "num_selected_clients": 10,
      "selected_clients": "0,1,2,3,4,5,6,7,8,9",
      "val_loss": 0.24134409791012956,
      "val_auroc": 0.9359625,
      "val_auprc": 0.8348566188206313,
      "val_acc": 0.888,
      "val_f1": 0.7383177570093458,
      "train_loss": 553.5890974602084,
      "train_auroc": 0.9648710730339004,
      "train_auprc": 0.9045786608331178,
      "train_acc": 0.9331401827501672,
      "train_f1": 0.8180280842510655,
      "is_personalized": true,
      "variant": "personal"
    },
    {
      "method": "ditto_concat_personal",
      "scenario": "FR_S0_congruent_iid",
      "seed": 11,
      "round": 62,
      "loss": 0.2637696772954509,
      "auroc": 0.9282888665997994,
      "auprc": 0.8036763792631008,
      "acc": 0.8628708901363272,
      "f1": 0.7046632124352331,
      "threshold": 0.19,
      "num_selected_clients": 10,
      "selected_clients": "0,1,2,3,4,5,6,7,8,9",
      "val_loss": 0.2439479125622253,
      "val_auroc": 0.9376875,
      "val_auprc": 0.832725299975238,
      "val_acc": 0.88,
      "val_f1": 0.7321428571428571,
      "train_loss": 569.9752848692984,
      "train_auroc": 0.9646892872345282,
      "train_auprc": 0.9072696317994591,
      "train_acc": 0.9340316469801649,
      "train_f1": 0.8234389950302667,
      "is_personalized": true,
      "variant": "personal"
    },
    {
      "method": "ditto_concat_personal",
      "scenario": "FR_S0_congruent_iid",
      "seed": 11,
      "round": 63,
      "loss": 0.2623980387514977,
      "auroc": 0.9279237713139418,
      "auprc": 0.8044565781873101,
      "acc": 0.8901363271852446,
      "f1": 0.7103594080338267,
      "threshold": 0.3999999999999999,
      "num_selected_clients": 10,
      "selected_clients": "0,1,2,3,4,5,6,7,8,9",
      "val_loss": 0.24300546854239696,
      "val_auroc": 0.9363625,
      "val_auprc": 0.8317052251671281,
      "val_acc": 0.898,
      "val_f1": 0.7301587301587301,
      "train_loss": 586.5889788126664,
      "train_auroc": 0.9667708783059544,
      "train_auprc": 0.9083065026846665,
      "train_acc": 0.9335859148651661,
      "train_f1": 0.8220934832216944,
      "is_personalized": true,
      "variant": "personal"
    },
    {
      "method": "ditto_concat_personal",
      "scenario": "FR_S0_congruent_iid",
      "seed": 11,
      "round": 64,
      "loss": 0.2615389764947122,
      "auroc": 0.9283370110330992,
      "auprc": 0.8052092293596432,
      "acc": 0.8877305533279871,
      "f1": 0.7058823529411765,
      "threshold": 0.37999999999999995,
      "num_selected_clients": 10,
      "selected_clients": "0,1,2,3,4,5,6,7,8,9",
      "val_loss": 0.2427755474486192,
      "val_auroc": 0.9368124999999999,
      "val_auprc": 0.8283407042825656,
      "val_acc": 0.896,
      "val_f1": 0.7263157894736842,
      "train_loss": 603.4407677838551,
      "train_auroc": 0.9653715089934176,
      "train_auprc": 0.9060876048040296,
      "train_acc": 0.9342545130376644,
      "train_f1": 0.824471798541036,
      "is_personalized": true,
      "variant": "personal"
    },
    {
      "method": "ditto_concat_personal",
      "scenario": "FR_S0_congruent_iid",
      "seed": 11,
      "round": 65,
      "loss": 0.262311900436941,
      "auroc": 0.9277111334002006,
      "auprc": 0.805177604315865,
      "acc": 0.8644747393744988,
      "f1": 0.7040280210157618,
      "threshold": 0.21499999999999997,
      "num_selected_clients": 10,
      "selected_clients": "0,1,2,3,4,5,6,7,8,9",
      "val_loss": 0.2423889434611752,
      "val_auroc": 0.9368125,
      "val_auprc": 0.8346320296792221,
      "val_acc": 0.884,
      "val_f1": 0.7387387387387387,
      "train_loss": 620.5087867730015,
      "train_auroc": 0.9673944187160269,
      "train_auprc": 0.9110429562319162,
      "train_acc": 0.9335859148651661,
      "train_f1": 0.8207794988099516,
      "is_personalized": true,
      "variant": "personal"
    },
    {
      "method": "ditto_concat_personal",
      "scenario": "FR_S0_congruent_iid",
      "seed": 11,
      "round": 66,
      "loss": 0.2606277936532079,
      "auroc": 0.9280421263791375,
      "auprc": 0.8058650297597006,
      "acc": 0.892542101042502,
      "f1": 0.7022222222222222,
      "threshold": 0.48499999999999993,
      "num_selected_clients": 10,
      "selected_clients": "0,1,2,3,4,5,6,7,8,9",
      "val_loss": 0.24117364216207066,
      "val_auroc": 0.93795,
      "val_auprc": 0.8338212081702674,
      "val_acc": 0.906,
      "val_f1": 0.7374301675977654,
      "train_loss": 637.852130483513,
      "train_auroc": 0.9682326269428786,
      "train_auprc": 0.9106393278154307,
      "train_acc": 0.9360374414976599,
      "train_f1": 0.8268541896655778,
      "is_personalized": true,
      "variant": "personal"
    },
    {
      "method": "ditto_concat_personal",
      "scenario": "FR_S0_congruent_iid",
      "seed": 11,
      "round": 67,
      "loss": 0.262293367075124,
      "auroc": 0.927667001003009,
      "auprc": 0.8063168117325381,
      "acc": 0.8740978348035284,
      "f1": 0.7160940325497287,
      "threshold": 0.29,
      "num_selected_clients": 10,
      "selected_clients": "0,1,2,3,4,5,6,7,8,9",
      "val_loss": 0.24231565523554344,
      "val_auroc": 0.9356875,
      "val_auprc": 0.8333139026912595,
      "val_acc": 0.884,
      "val_f1": 0.7339449541284404,
      "train_loss": 655.4206971835262,
      "train_auroc": 0.967882131777316,
      "train_auprc": 0.913193694245561,
      "train_acc": 0.9353688433251616,
      "train_f1": 0.8248202424355865,
      "is_personalized": true,
      "variant": "personal"
    },
    {
      "method": "ditto_concat_personal",
      "scenario": "FR_S0_congruent_iid",
      "seed": 11,
      "round": 68,
      "loss": 0.26095119714886583,
      "auroc": 0.9279819458375125,
      "auprc": 0.8078056020484837,
      "acc": 0.8901363271852446,
      "f1": 0.7015250544662309,
      "threshold": 0.4699999999999999,
      "num_selected_clients": 10,
      "selected_clients": "0,1,2,3,4,5,6,7,8,9",
      "val_loss": 0.24156119815553326,
      "val_auroc": 0.9368374999999999,
      "val_auprc": 0.8343105192594265,
      "val_acc": 0.902,
      "val_f1": 0.7292817679558011,
      "train_loss": 673.2233474974593,
      "train_auroc": 0.9681987280698184,
      "train_auprc": 0.9114753020218691,
      "train_acc": 0.9347002451526633,
      "train_f1": 0.824620156793643,
      "is_personalized": true,
      "variant": "personal"
    },
    {
      "method": "ditto_concat_personal",
      "scenario": "FR_S0_congruent_iid",
      "seed": 11,
      "round": 69,
      "loss": 0.26045202197533024,
      "auroc": 0.9281624874623872,
      "auprc": 0.8080432131217485,
      "acc": 0.8917401764234162,
      "f1": 0.7032967032967034,
      "threshold": 0.4549999999999999,
      "num_selected_clients": 10,
      "selected_clients": "0,1,2,3,4,5,6,7,8,9",
      "val_loss": 0.24241371946713447,
      "val_auroc": 0.9364625,
      "val_auprc": 0.8355760544344937,
      "val_acc": 0.904,
      "val_f1": 0.7333333333333333,
      "train_loss": 691.2611045616359,
      "train_auroc": 0.969830456514468,
      "train_auprc": 0.9170266719677027,
      "train_acc": 0.9351459772676621,
      "train_f1": 0.8259116143603171,
      "is_personalized": true,
      "variant": "personal"
    },
    {
      "method": "ditto_concat_personal",
      "scenario": "FR_S0_congruent_iid",
      "seed": 11,
      "round": 70,
      "loss": 0.26465455652400016,
      "auroc": 0.9275606820461384,
      "auprc": 0.8018963529404095,
      "acc": 0.8797113071371291,
      "f1": 0.6975806451612904,
      "threshold": 0.3999999999999999,
      "num_selected_clients": 10,
      "selected_clients": "0,1,2,3,4,5,6,7,8,9",
      "val_loss": 0.24362524834906674,
      "val_auroc": 0.9362125,
      "val_auprc": 0.8256818459067164,
      "val_acc": 0.892,
      "val_f1": 0.7272727272727273,
      "train_loss": 709.5009621955356,
      "train_auroc": 0.9698416489939038,
      "train_auprc": 0.91619849715154,
      "train_acc": 0.9375975039001561,
      "train_f1": 0.8322894264672069,
      "is_personalized": true,
      "variant": "personal"
    },
    {
      "method": "ditto_concat_personal",
      "scenario": "FR_S0_congruent_iid",
      "seed": 11,
      "round": 71,
      "loss": 0.2594504564562695,
      "auroc": 0.927681043129388,
      "auprc": 0.8088947308951243,
      "acc": 0.867682437850842,
      "f1": 0.7048300536672629,
      "threshold": 0.26499999999999996,
      "num_selected_clients": 10,
      "selected_clients": "0,1,2,3,4,5,6,7,8,9",
      "val_loss": 0.24268390669572343,
      "val_auroc": 0.93475,
      "val_auprc": 0.8348016140450752,
      "val_acc": 0.886,
      "val_f1": 0.7397260273972602,
      "train_loss": 728.046460361451,
      "train_auroc": 0.9695811456781127,
      "train_auprc": 0.9142574592543791,
      "train_acc": 0.9387118341876532,
      "train_f1": 0.8340561281819256,
      "is_personalized": true,
      "variant": "personal"
    },
    {
      "method": "ditto_concat_personal",
      "scenario": "FR_S0_congruent_iid",
      "seed": 11,
      "round": 72,
      "loss": 0.26184968565818756,
      "auroc": 0.9282186559679038,
      "auprc": 0.8052785823978931,
      "acc": 0.8917401764234162,
      "f1": 0.7096774193548387,
      "threshold": 0.43499999999999994,
      "num_selected_clients": 10,
      "selected_clients": "0,1,2,3,4,5,6,7,8,9",
      "val_loss": 0.24110711809620455,
      "val_auroc": 0.93765,
      "val_auprc": 0.8330751341923265,
      "val_acc": 0.9,
      "val_f1": 0.7340425531914894,
      "train_loss": 746.7603656763698,
      "train_auroc": 0.968440781034361,
      "train_auprc": 0.9164794181260413,
      "train_acc": 0.9342545130376644,
      "train_f1": 0.8231251495066895,
      "is_personalized": true,
      "variant": "personal"
    },
    {
      "method": "ditto_concat_personal",
      "scenario": "FR_S0_congruent_iid",
      "seed": 11,
      "round": 73,
      "loss": 0.26230031302017515,
      "auroc": 0.9269147442326982,
      "auprc": 0.8064391548832561,
      "acc": 0.8901363271852446,
      "f1": 0.7091295116772823,
      "threshold": 0.4499999999999999,
      "num_selected_clients": 10,
      "selected_clients": "0,1,2,3,4,5,6,7,8,9",
      "val_loss": 0.24347761918369693,
      "val_auroc": 0.9335625000000001,
      "val_auprc": 0.8309462817006974,
      "val_acc": 0.9,
      "val_f1": 0.7340425531914894,
      "train_loss": 765.7111656978769,
      "train_auroc": 0.9699898979880445,
      "train_auprc": 0.9177669842752374,
      "train_acc": 0.9362603075551593,
      "train_f1": 0.8296343715382648,
      "is_personalized": true,
      "variant": "personal"
    },
    {
      "method": "ditto_concat_personal",
      "scenario": "FR_S0_congruent_iid",
      "seed": 11,
      "round": 74,
      "loss": 0.26168968054467334,
      "auroc": 0.928481444332999,
      "auprc": 0.8069974945851495,
      "acc": 0.8933440256615878,
      "f1": 0.712742980561555,
      "threshold": 0.49499999999999994,
      "num_selected_clients": 10,
      "selected_clients": "0,1,2,3,4,5,6,7,8,9",
      "val_loss": 0.24060854631245304,
      "val_auroc": 0.9373999999999999,
      "val_auprc": 0.8347706319198683,
      "val_acc": 0.902,
      "val_f1": 0.73224043715847,
      "train_loss": 784.9813468695909,
      "train_auroc": 0.971391798222602,
      "train_auprc": 0.9207120245119165,
      "train_acc": 0.9358145754401604,
      "train_f1": 0.8281273658413246,
      "is_personalized": true,
      "variant": "personal"
    },
    {
      "method": "ditto_concat_personal",
      "scenario": "FR_S0_congruent_iid",
      "seed": 11,
      "round": 75,
      "loss": 0.26751049192760123,
      "auroc": 0.9289207622868605,
      "auprc": 0.8089775103294065,
      "acc": 0.892542101042502,
      "f1": 0.7008928571428571,
      "threshold": 0.39499999999999996,
      "num_selected_clients": 10,
      "selected_clients": "0,1,2,3,4,5,6,7,8,9",
      "val_loss": 0.24832927339698546,
      "val_auroc": 0.9390875000000001,
      "val_auprc": 0.8384349180187616,
      "val_acc": 0.91,
      "val_f1": 0.7486033519553073,
      "train_loss": 804.4720576375371,
      "train_auroc": 0.9709991772267677,
      "train_auprc": 0.9180901739748838,
      "train_acc": 0.9371517717851571,
      "train_f1": 0.8337439208623593,
      "is_personalized": true,
      "variant": "personal"
    },
    {
      "method": "ditto_concat_personal",
      "scenario": "FR_S0_congruent_iid",
      "seed": 11,
      "round": 76,
      "loss": 0.26127677609539135,
      "auroc": 0.9281544633901706,
      "auprc": 0.8090006786835628,
      "acc": 0.8933440256615878,
      "f1": 0.70509977827051,
      "threshold": 0.48999999999999994,
      "num_selected_clients": 10,
      "selected_clients": "0,1,2,3,4,5,6,7,8,9",
      "val_loss": 0.2417088863332319,
      "val_auroc": 0.9370249999999999,
      "val_auprc": 0.8350452040407613,
      "val_acc": 0.908,
      "val_f1": 0.7415730337078652,
      "train_loss": 824.1467356608497,
      "train_auroc": 0.9727224920221778,
      "train_auprc": 0.9245932949280447,
      "train_acc": 0.9393804323601516,
      "train_f1": 0.8389062012085918,
      "is_personalized": true,
      "variant": "personal"
    },
    {
      "method": "ditto_concat_personal",
      "scenario": "FR_S0_congruent_iid",
      "seed": 11,
      "round": 77,
      "loss": 0.26577581874639333,
      "auroc": 0.9272998996990973,
      "auprc": 0.80394215914368,
      "acc": 0.892542101042502,
      "f1": 0.7086956521739131,
      "threshold": 0.5099999999999999,
      "num_selected_clients": 10,
      "selected_clients": "0,1,2,3,4,5,6,7,8,9",
      "val_loss": 0.24404347109274094,
      "val_auroc": 0.93515,
      "val_auprc": 0.8271560401477668,
      "val_acc": 0.904,
      "val_f1": 0.7419354838709677,
      "train_loss": 844.1056203878295,
      "train_auroc": 0.9719101906818981,
      "train_auprc": 0.923224848056596,
      "train_acc": 0.9400490305326499,
      "train_f1": 0.8401886938174808,
      "is_personalized": true,
      "variant": "personal"
    },
    {
      "method": "ditto_concat_personal",
      "scenario": "FR_S0_congruent_iid",
      "seed": 11,
      "round": 78,
      "loss": 0.2611768693094196,
      "auroc": 0.9286680040120361,
      "auprc": 0.8076917416780396,
      "acc": 0.8941459502806736,
      "f1": 0.7066666666666667,
      "threshold": 0.49499999999999994,
      "num_selected_clients": 10,
      "selected_clients": "0,1,2,3,4,5,6,7,8,9",
      "val_loss": 0.24175255491133885,
      "val_auroc": 0.9382625,
      "val_auprc": 0.8352614372567844,
      "val_acc": 0.908,
      "val_f1": 0.7415730337078652,
      "train_loss": 864.3036529506159,
      "train_auroc": 0.9741434249474298,
      "train_auprc": 0.9258690213014873,
      "train_acc": 0.9418319589926454,
      "train_f1": 0.8443316621979845,
      "is_personalized": true,
      "variant": "personal"
    },
    {
      "method": "ditto_concat_personal",
      "scenario": "FR_S0_congruent_iid",
      "seed": 11,
      "round": 79,
      "loss": 0.261472172599806,
      "auroc": 0.9272357071213639,
      "auprc": 0.8071662603578966,
      "acc": 0.892542101042502,
      "f1": 0.7048458149779736,
      "threshold": 0.5149999999999999,
      "num_selected_clients": 10,
      "selected_clients": "0,1,2,3,4,5,6,7,8,9",
      "val_loss": 0.2416377290088181,
      "val_auroc": 0.9351999999999999,
      "val_auprc": 0.8351981096177067,
      "val_acc": 0.908,
      "val_f1": 0.7415730337078652,
      "train_loss": 884.7296375068918,
      "train_auroc": 0.9743462959330381,
      "train_auprc": 0.9283750486734106,
      "train_acc": 0.9418319589926454,
      "train_f1": 0.8449455791789301,
      "is_personalized": true,
      "variant": "personal"
    },
    {
      "method": "ditto_concat_personal",
      "scenario": "FR_S0_congruent_iid",
      "seed": 11,
      "round": 80,
      "loss": 0.2623230714993008,
      "auroc": 0.9279257773319959,
      "auprc": 0.8063860433799191,
      "acc": 0.8909382518043304,
      "f1": 0.6977777777777778,
      "threshold": 0.5249999999999999,
      "num_selected_clients": 10,
      "selected_clients": "0,1,2,3,4,5,6,7,8,9",
      "val_loss": 0.2438847317764954,
      "val_auroc": 0.9361125000000001,
      "val_auprc": 0.8294684575298719,
      "val_acc": 0.908,
      "val_f1": 0.7415730337078652,
      "train_loss": 905.411116870177,
      "train_auroc": 0.9719980338885874,
      "train_auprc": 0.9242780265746448,
      "train_acc": 0.9404947626476488,
      "train_f1": 0.840646438652211,
      "is_personalized": true,
      "variant": "personal"
    },
    {
      "method": "ditto_concat_personal",
      "scenario": "FR_S0_congruent_iid",
      "seed": 11,
      "round": 81,
      "loss": 0.26570595032671573,
      "auroc": 0.9275025075225677,
      "auprc": 0.8058909066227952,
      "acc": 0.8917401764234162,
      "f1": 0.7032967032967034,
      "threshold": 0.39499999999999996,
      "num_selected_clients": 10,
      "selected_clients": "0,1,2,3,4,5,6,7,8,9",
      "val_loss": 0.2480448798384847,
      "val_auroc": 0.93615,
      "val_auprc": 0.8327143640067242,
      "val_acc": 0.908,
      "val_f1": 0.7444444444444445,
      "train_loss": 926.3125623342107,
      "train_auroc": 0.9761041135421331,
      "train_auprc": 0.9313626506285835,
      "train_acc": 0.9467350122576331,
      "train_f1": 0.8604716353660542,
      "is_personalized": true,
      "variant": "personal"
    },
    {
      "method": "ditto_concat_personal",
      "scenario": "FR_S0_congruent_iid",
      "seed": 11,
      "round": 82,
      "loss": 0.25935902855916393,
      "auroc": 0.928593781344032,
      "auprc": 0.8101035760561808,
      "acc": 0.8949478748997595,
      "f1": 0.7108167770419426,
      "threshold": 0.48499999999999993,
      "num_selected_clients": 10,
      "selected_clients": "0,1,2,3,4,5,6,7,8,9",
      "val_loss": 0.24056801496500213,
      "val_auroc": 0.9376249999999999,
      "val_auprc": 0.8371796548146427,
      "val_acc": 0.908,
      "val_f1": 0.7415730337078652,
      "train_loss": 947.4763093471846,
      "train_auroc": 0.9746283152921907,
      "train_auprc": 0.9273702885986136,
      "train_acc": 0.9402718965901493,
      "train_f1": 0.8401049291212825,
      "is_personalized": true,
      "variant": "personal"
    },
    {
      "method": "ditto_concat_personal",
      "scenario": "FR_S0_congruent_iid",
      "seed": 11,
      "round": 83,
      "loss": 0.25905019752560976,
      "auroc": 0.9285997993981945,
      "auprc": 0.8117929849991388,
      "acc": 0.8949478748997595,
      "f1": 0.7095343680709535,
      "threshold": 0.4799999999999999,
      "num_selected_clients": 10,
      "selected_clients": "0,1,2,3,4,5,6,7,8,9",
      "val_loss": 0.24405978956303287,
      "val_auroc": 0.9357,
      "val_auprc": 0.8356878290799619,
      "val_acc": 0.91,
      "val_f1": 0.7486033519553073,
      "train_loss": 968.8627293507878,
      "train_auroc": 0.976348701509496,
      "train_auprc": 0.9332976091279339,
      "train_acc": 0.9442834856251393,
      "train_f1": 0.8502553929303182,
      "is_personalized": true,
      "variant": "personal"
    },
    {
      "method": "ditto_concat_personal",
      "scenario": "FR_S0_congruent_iid",
      "seed": 11,
      "round": 84,
      "loss": 0.26438473143844954,
      "auroc": 0.9269307923771315,
      "auprc": 0.8084512873908235,
      "acc": 0.892542101042502,
      "f1": 0.7112068965517241,
      "threshold": 0.48499999999999993,
      "num_selected_clients": 10,
      "selected_clients": "0,1,2,3,4,5,6,7,8,9",
      "val_loss": 0.2448871022092524,
      "val_auroc": 0.93645,
      "val_auprc": 0.834338846992301,
      "val_acc": 0.9,
      "val_f1": 0.7340425531914894,
      "train_loss": 990.5152570704508,
      "train_auroc": 0.9738900686946899,
      "train_auprc": 0.9285056849802458,
      "train_acc": 0.9440606195676399,
      "train_f1": 0.8487828628980897,
      "is_personalized": true,
      "variant": "personal"
    },
    {
      "method": "ditto_concat_personal",
      "scenario": "FR_S0_congruent_iid",
      "seed": 11,
      "round": 85,
      "loss": 0.2619161415138766,
      "auroc": 0.927654964894684,
      "auprc": 0.8081127744887396,
      "acc": 0.8933440256615878,
      "f1": 0.7064017660044151,
      "threshold": 0.5049999999999999,
      "num_selected_clients": 10,
      "selected_clients": "0,1,2,3,4,5,6,7,8,9",
      "val_loss": 0.24431265385675782,
      "val_auroc": 0.9358375,
      "val_auprc": 0.8310840036939943,
      "val_acc": 0.906,
      "val_f1": 0.7374301675977654,
      "train_loss": 1012.3680940474596,
      "train_auroc": 0.9770865649517156,
      "train_auprc": 0.9348912658535841,
      "train_acc": 0.9465121462001337,
      "train_f1": 0.8565912351009942,
      "is_personalized": true,
      "variant": "personal"
    },
    {
      "method": "ditto_concat_personal",
      "scenario": "FR_S0_congruent_iid",
      "seed": 11,
      "round": 86,
      "loss": 0.26034919118873184,
      "auroc": 0.9282407221664996,
      "auprc": 0.8073805489744936,
      "acc": 0.8917401764234162,
      "f1": 0.7019867549668874,
      "threshold": 0.5049999999999999,
      "num_selected_clients": 10,
      "selected_clients": "0,1,2,3,4,5,6,7,8,9",
      "val_loss": 0.2427900548275402,
      "val_auroc": 0.93685,
      "val_auprc": 0.8331447434941135,
      "val_acc": 0.908,
      "val_f1": 0.7415730337078652,
      "train_loss": 1034.4852772587947,
      "train_auroc": 0.9748230838943092,
      "train_auprc": 0.9305209874369229,
      "train_acc": 0.9425005571651438,
      "train_f1": 0.8473118730691821,
      "is_personalized": true,
      "variant": "personal"
    },
    {
      "method": "ditto_concat_personal",
      "scenario": "FR_S0_congruent_iid",
      "seed": 11,
      "round": 87,
      "loss": 0.2632731276538243,
      "auroc": 0.9263971915747243,
      "auprc": 0.8087022923501866,
      "acc": 0.892542101042502,
      "f1": 0.7048458149779736,
      "threshold": 0.5299999999999999,
      "num_selected_clients": 10,
      "selected_clients": "0,1,2,3,4,5,6,7,8,9",
      "val_loss": 0.24408591610566946,
      "val_auroc": 0.934825,
      "val_auprc": 0.8331604019799218,
      "val_acc": 0.904,
      "val_f1": 0.7303370786516854,
      "train_loss": 1056.8830420326385,
      "train_auroc": 0.9768735080890174,
      "train_auprc": 0.9330912090147702,
      "train_acc": 0.9420548250501448,
      "train_f1": 0.8470584008076922,
      "is_personalized": true,
      "variant": "personal"
    },
    {
      "method": "ditto_concat_personal",
      "scenario": "FR_S0_congruent_iid",
      "seed": 11,
      "round": 88,
      "loss": 0.26305324103534206,
      "auroc": 0.9263249749247743,
      "auprc": 0.808356671012674,
      "acc": 0.8917401764234162,
      "f1": 0.7006651884700665,
      "threshold": 0.5099999999999999,
      "num_selected_clients": 10,
      "selected_clients": "0,1,2,3,4,5,6,7,8,9",
      "val_loss": 0.2448185569265644,
      "val_auroc": 0.9339124999999999,
      "val_auprc": 0.8316963072792944,
      "val_acc": 0.906,
      "val_f1": 0.7374301675977654,
      "train_loss": 1079.512795229598,
      "train_auroc": 0.9764829371642749,
      "train_auprc": 0.9322351727765044,
      "train_acc": 0.9456206819701359,
      "train_f1": 0.8562981415681946,
      "is_personalized": true,
      "variant": "personal"
    },
    {
      "method": "ditto_concat_personal",
      "scenario": "FR_S0_congruent_iid",
      "seed": 11,
      "round": 89,
      "loss": 0.2608664654427382,
      "auroc": 0.9276810431293881,
      "auprc": 0.8107208746278666,
      "acc": 0.8933440256615878,
      "f1": 0.70509977827051,
      "threshold": 0.5299999999999999,
      "num_selected_clients": 10,
      "selected_clients": "0,1,2,3,4,5,6,7,8,9",
      "val_loss": 0.24129522690617483,
      "val_auroc": 0.9357875,
      "val_auprc": 0.8347711018999615,
      "val_acc": 0.908,
      "val_f1": 0.7415730337078652,
      "train_loss": 1102.3337883078923,
      "train_auroc": 0.9785445672992132,
      "train_auprc": 0.9365464072450593,
      "train_acc": 0.9440606195676399,
      "train_f1": 0.849946318516573,
      "is_personalized": true,
      "variant": "personal"
    },
    {
      "method": "ditto_concat_personal",
      "scenario": "FR_S0_congruent_iid",
      "seed": 11,
      "round": 90,
      "loss": 0.2660757615608842,
      "auroc": 0.9279277833500501,
      "auprc": 0.8092423240512743,
      "acc": 0.8957497995188453,
      "f1": 0.7123893805309734,
      "threshold": 0.42499999999999993,
      "num_selected_clients": 10,
      "selected_clients": "0,1,2,3,4,5,6,7,8,9",
      "val_loss": 0.24752842384296184,
      "val_auroc": 0.9375625,
      "val_auprc": 0.836335576422796,
      "val_acc": 0.91,
      "val_f1": 0.7486033519553073,
      "train_loss": 1125.407372102085,
      "train_auroc": 0.9772731802504055,
      "train_auprc": 0.9358727989611255,
      "train_acc": 0.9449520837976376,
      "train_f1": 0.8548722310607393,
      "is_personalized": true,
      "variant": "personal"
    },
    {
      "method": "ditto_concat_personal",
      "scenario": "FR_S0_congruent_iid",
      "seed": 11,
      "round": 91,
      "loss": 0.26397218320000365,
      "auroc": 0.9277953861584755,
      "auprc": 0.8083645997441393,
      "acc": 0.892542101042502,
      "f1": 0.7022222222222222,
      "threshold": 0.4649999999999999,
      "num_selected_clients": 10,
      "selected_clients": "0,1,2,3,4,5,6,7,8,9",
      "val_loss": 0.2455948780995444,
      "val_auroc": 0.9374750000000001,
      "val_auprc": 0.8343898779038027,
      "val_acc": 0.91,
      "val_f1": 0.7486033519553073,
      "train_loss": 1148.7630807201979,
      "train_auroc": 0.9769588604326358,
      "train_auprc": 0.9344006649351706,
      "train_acc": 0.9465121462001337,
      "train_f1": 0.8591428995872831,
      "is_personalized": true,
      "variant": "personal"
    },
    {
      "method": "ditto_concat_personal",
      "scenario": "FR_S0_congruent_iid",
      "seed": 11,
      "round": 92,
      "loss": 0.2612182883818509,
      "auroc": 0.9281123370110331,
      "auprc": 0.807169860145091,
      "acc": 0.8893344025661588,
      "f1": 0.6960352422907489,
      "threshold": 0.4799999999999999,
      "num_selected_clients": 10,
      "selected_clients": "0,1,2,3,4,5,6,7,8,9",
      "val_loss": 0.2420699002187352,
      "val_auroc": 0.9378875,
      "val_auprc": 0.8315761036896185,
      "val_acc": 0.908,
      "val_f1": 0.7444444444444445,
      "train_loss": 1172.307226598462,
      "train_auroc": 0.9800141178504431,
      "train_auprc": 0.9414325865198554,
      "train_acc": 0.947626476487631,
      "train_f1": 0.8599977061593386,
      "is_personalized": true,
      "variant": "personal"
    },
    {
      "method": "ditto_concat_personal",
      "scenario": "FR_S0_congruent_iid",
      "seed": 11,
      "round": 93,
      "loss": 0.26787230174362686,
      "auroc": 0.926778335005015,
      "auprc": 0.8070104017597447,
      "acc": 0.8941459502806736,
      "f1": 0.7066666666666667,
      "threshold": 0.42999999999999994,
      "num_selected_clients": 10,
      "selected_clients": "0,1,2,3,4,5,6,7,8,9",
      "val_loss": 0.2503546503546476,
      "val_auroc": 0.936375,
      "val_auprc": 0.8349824996375937,
      "val_acc": 0.91,
      "val_f1": 0.7486033519553073,
      "train_loss": 1196.084469552717,
      "train_auroc": 0.9785517275295007,
      "train_auprc": 0.9376345276362147,
      "train_acc": 0.9469578783151326,
      "train_f1": 0.8616354392343235,
      "is_personalized": true,
      "variant": "personal"
    },
    {
      "method": "ditto_concat_personal",
      "scenario": "FR_S0_congruent_iid",
      "seed": 11,
      "round": 94,
      "loss": 0.25968243122145745,
      "auroc": 0.9281805416248746,
      "auprc": 0.8119562061431149,
      "acc": 0.8957497995188453,
      "f1": 0.7136563876651982,
      "threshold": 0.4749999999999999,
      "num_selected_clients": 10,
      "selected_clients": "0,1,2,3,4,5,6,7,8,9",
      "val_loss": 0.24272354250838307,
      "val_auroc": 0.9362750000000001,
      "val_auprc": 0.8365982373710398,
      "val_acc": 0.91,
      "val_f1": 0.7486033519553073,
      "train_loss": 1220.0967517556926,
      "train_auroc": 0.9781081111951306,
      "train_auprc": 0.9391520792138833,
      "train_acc": 0.9480722086026299,
      "train_f1": 0.862313066670919,
      "is_personalized": true,
      "variant": "personal"
    },
    {
      "method": "ditto_concat_personal",
      "scenario": "FR_S0_congruent_iid",
      "seed": 11,
      "round": 95,
      "loss": 0.2648898991401689,
      "auroc": 0.9257973921765297,
      "auprc": 0.808066541507155,
      "acc": 0.892542101042502,
      "f1": 0.7022222222222222,
      "threshold": 0.49499999999999994,
      "num_selected_clients": 10,
      "selected_clients": "0,1,2,3,4,5,6,7,8,9",
      "val_loss": 0.2449330357294378,
      "val_auroc": 0.9345,
      "val_auprc": 0.8326857790748344,
      "val_acc": 0.906,
      "val_f1": 0.7374301675977654,
      "train_loss": 1244.3815491129885,
      "train_auroc": 0.9793962974141612,
      "train_auprc": 0.9420494987729585,
      "train_acc": 0.951192333407622,
      "train_f1": 0.8721718021455888,
      "is_personalized": true,
      "variant": "personal"
    },
    {
      "method": "ditto_concat_personal",
      "scenario": "FR_S0_congruent_iid",
      "seed": 11,
      "round": 96,
      "loss": 0.2614202308582396,
      "auroc": 0.9280200601805416,
      "auprc": 0.8089832838882026,
      "acc": 0.8917401764234162,
      "f1": 0.7019867549668874,
      "threshold": 0.4749999999999999,
      "num_selected_clients": 10,
      "selected_clients": "0,1,2,3,4,5,6,7,8,9",
      "val_loss": 0.2421012952853264,
      "val_auroc": 0.938,
      "val_auprc": 0.8353579710193266,
      "val_acc": 0.908,
      "val_f1": 0.7444444444444445,
      "train_loss": 1268.8885128258437,
      "train_auroc": 0.9803676148809459,
      "train_auprc": 0.9419145808430034,
      "train_acc": 0.9485179407176287,
      "train_f1": 0.8637802851489164,
      "is_personalized": true,
      "variant": "personal"
    },
    {
      "method": "ditto_concat_personal",
      "scenario": "FR_S0_congruent_iid",
      "seed": 11,
      "round": 97,
      "loss": 0.2660844677956145,
      "auroc": 0.9260641925777331,
      "auprc": 0.804017175056633,
      "acc": 0.8917401764234162,
      "f1": 0.7071583514099783,
      "threshold": 0.4699999999999999,
      "num_selected_clients": 10,
      "selected_clients": "0,1,2,3,4,5,6,7,8,9",
      "val_loss": 0.24409944522710134,
      "val_auroc": 0.9360875,
      "val_auprc": 0.8310083625159481,
      "val_acc": 0.906,
      "val_f1": 0.745945945945946,
      "train_loss": 1293.6318470113442,
      "train_auroc": 0.9807399171348965,
      "train_auprc": 0.9426962946917392,
      "train_acc": 0.9503008691776242,
      "train_f1": 0.8686077297095067,
      "is_personalized": true,
      "variant": "personal"
    },
    {
      "method": "ditto_concat_personal",
      "scenario": "FR_S0_congruent_iid",
      "seed": 11,
      "round": 98,
      "loss": 0.26595216788738396,
      "auroc": 0.9271073219658976,
      "auprc": 0.8071203873485289,
      "acc": 0.892542101042502,
      "f1": 0.7008928571428571,
      "threshold": 0.43999999999999995,
      "num_selected_clients": 10,
      "selected_clients": "0,1,2,3,4,5,6,7,8,9",
      "val_loss": 0.24580943463369934,
      "val_auroc": 0.9369249999999999,
      "val_auprc": 0.8354222816851372,
      "val_acc": 0.912,
      "val_f1": 0.7528089887640449,
      "train_loss": 1318.6284449186041,
      "train_auroc": 0.9800735141993391,
      "train_auprc": 0.942325773272065,
      "train_acc": 0.9498551370626254,
      "train_f1": 0.8678676106801603,
      "is_personalized": true,
      "variant": "personal"
    },
    {
      "method": "ditto_concat_personal",
      "scenario": "FR_S0_congruent_iid",
      "seed": 11,
      "round": 99,
      "loss": 0.265534620833599,
      "auroc": 0.9270371113340019,
      "auprc": 0.8066328584735762,
      "acc": 0.8909382518043304,
      "f1": 0.7043478260869566,
      "threshold": 0.49999999999999994,
      "num_selected_clients": 10,
      "selected_clients": "0,1,2,3,4,5,6,7,8,9",
      "val_loss": 0.2433479273326385,
      "val_auroc": 0.9359374999999999,
      "val_auprc": 0.8299011008656254,
      "val_acc": 0.906,
      "val_f1": 0.7431693989071039,
      "train_loss": 1343.8222529779225,
      "train_auroc": 0.9819320826651241,
      "train_auprc": 0.9467796493489996,
      "train_acc": 0.9527523958101182,
      "train_f1": 0.8765342350759232,
      "is_personalized": true,
      "variant": "personal"
    },
    {
      "method": "ditto_concat_personal",
      "scenario": "FR_S0_congruent_iid",
      "seed": 11,
      "round": 100,
      "loss": 0.26399937987208416,
      "auroc": 0.927913741223671,
      "auprc": 0.811155945694061,
      "acc": 0.892542101042502,
      "f1": 0.6981981981981982,
      "threshold": 0.44499999999999995,
      "num_selected_clients": 10,
      "selected_clients": "0,1,2,3,4,5,6,7,8,9",
      "val_loss": 0.24686457529026193,
      "val_auroc": 0.937325,
      "val_auprc": 0.8387757180723313,
      "val_acc": 0.91,
      "val_f1": 0.7486033519553073,
      "train_loss": 1369.3318613573945,
      "train_auroc": 0.9800985866272899,
      "train_auprc": 0.9428701814869842,
      "train_acc": 0.9500780031201248,
      "train_f1": 0.8683249932980269,
      "is_personalized": true,
      "variant": "personal"
    }
  ]
}